{"_ts":[1535762557],"_r":{"breakdown":{"html":{"bytes":[45639],"requests":[56]},"js":{"bytes":[1280478],"requests":[74]},"css":{"bytes":[276794],"requests":[10]},"image":{"bytes":[1858190],"requests":[115]},"flash":{"bytes":[0],"requests":[0]},"font":{"bytes":[243077],"requests":[11]},"video":{"bytes":[0],"requests":[0]},"other":{"bytes":[51708],"requests":[37]}},"date":[1535762557],"domElements":[1852.5],"domInteractive":[5465.5],"firstPaint":[5151.3499999983],"fullyLoaded":[17561.5],"id":["180901_5V_0d7f4a420e0728496265b15ff39d5b26"],"loadTime":[12952],"render":[5200],"SpeedIndex":[5543],"TTFB":[2416.5],"videoFrames":[[{"_i":"ms_000000.jpg","_t":0,"_vc":0},{"_i":"ms_007300.jpg","_t":7300,"_vc":54},{"_i":"ms_007600.jpg","_t":7600,"_vc":76},{"_i":"ms_007800.jpg","_t":7800,"_vc":76},{"_i":"ms_007900.jpg","_t":7900,"_vc":74},{"_i":"ms_008000.jpg","_t":8000,"_vc":96},{"_i":"ms_010500.jpg","_t":10500,"_vc":99},{"_i":"ms_011200.jpg","_t":11200,"_vc":96},{"_i":"ms_011300.jpg","_t":11300,"_vc":99},{"_i":"ms_011600.jpg","_t":11600,"_vc":99},{"_i":"ms_011700.jpg","_t":11700,"_vc":99},{"_i":"ms_012100.jpg","_t":12100,"_vc":99},{"_i":"ms_012300.jpg","_t":12300,"_vc":99},{"_i":"ms_012900.jpg","_t":12900,"_vc":99},{"_i":"ms_013300.jpg","_t":13300,"_vc":99},{"_i":"ms_013600.jpg","_t":13600,"_vc":99},{"_i":"ms_014200.jpg","_t":14200,"_vc":99},{"_i":"ms_014400.jpg","_t":14400,"_vc":99},{"_i":"ms_014600.jpg","_t":14600,"_vc":99},{"_i":"ms_014900.jpg","_t":14900,"_vc":99},{"_i":"ms_015100.jpg","_t":15100,"_vc":99},{"_i":"ms_015300.jpg","_t":15300,"_vc":100},{"_i":"ms_015400.jpg","_t":15400,"_vc":100}]],"visualComplete":[11100],"lighthouse":[31],"pagespeed":[50]}}